faassa/__init__.py
faassa/api.py
faassa/demo_server.py
faassa/faas_storage_agent_pb2.py
faassa/faas_storage_agent_pb2_grpc.py
faassa/test_server.py
tests/__init__.py
tests/test_api.py
faassa-0.1.8.dist-info/.gitignore
faassa-0.1.8.dist-info/METADATA
faassa-0.1.8.dist-info/WHEEL
faassa-0.1.8.dist-info/top_level.txt
faassa-0.1.8.dist-info/RECORD
